{
  "analysis_schema_version": 3,
  "id": "49c7a79ba059",
  "year": "2025",
  "date": "2025-12-18",
  "title": "透过巨头的广告策略，预见下一个风口",
  "relative_path": "2025/2025-12-18_透过巨头的广告策略，预见下一个风口.txt",
  "full_text_path": "C:\\Users\\LXG\\AI_writer\\style_corpora\\huxiu\\raw_materials\\2025\\2025-12-18_透过巨头的广告策略，预见下一个风口.txt",
  "char_count": 2964,
  "content_type": "商业趋势观察",
  "entities": [
    "文化和旅游部",
    "中央广播电视总台",
    "广东文旅",
    "贵州茅台",
    "安利纽崔莱",
    "鲁南制药",
    "中粮福临门",
    "海尔卡萨帝",
    "格力电器",
    "绿源电动车",
    "小鹏汽车"
  ],
  "industry": [
    "广告营销",
    "快消品",
    "文旅",
    "大健康",
    "智能家居",
    "新能源汽车"
  ],
  "topic": [
    "消费趋势预判",
    "品牌营销策略",
    "媒介价值分析",
    "2025市场风口"
  ],
  "genre": "行业综述",
  "style": [
    "归纳法",
    "案例驱动",
    "宏大叙事"
  ],
  "audience": [
    "品牌营销从业者",
    "企业高管",
    "市场分析师",
    "媒体策划"
  ],
  "intent": [
    "趋势解读",
    "品牌背书",
    "策略建议"
  ],
  "tone": [
    "前瞻性",
    "赞美性",
    "专业"
  ],
  "primary_question": "2025年品牌主广告预算的流向揭示了哪些核心消费趋势？",
  "thesis_type": "归纳型论证",
  "thesis_sentence": "广告预算是消费心电图，2025年品牌正通过情绪价值、全面健康、智能科技、绿色环保四大赛道，借助权威平台背书，实现从产品宣讲到价值观认同的转变。",
  "structure_pattern": "总-分-总（趋势分类式）",
  "section_functions": [
    "引言：以预算比喻趋势，引出四大增长密码",
    "趋势一：分析情绪价值及文旅/酒类跨界案例",
    "趋势二：探讨大健康产业与权威媒体背书的结合",
    "趋势三：解读智能科技产品如何通过场景化内容落地",
    "趋势四：论述绿色环保趋势在出行领域的营销实践",
    "结语：总结消费逻辑转变，强调公信力平台的价值"
  ],
  "argument_moves": [
    "提出核心隐喻（预算即心电图）",
    "引用官方统计数据确立行业背景",
    "拆分具体维度进行细分论证",
    "罗列头部企业成功案例作为实证",
    "提炼案例背后的商业本质（从功能到情怀）",
    "升华至社会信任与集体情感的高度"
  ],
  "core_argument": "品牌成功的关键在于顺应消费者的价值主张变迁，并利用高公信力平台进行内容共创，将商业表达转化为社会共识。",
  "key_points": [
    "情绪价值成为大众常态，沉浸式营销取代硬广",
    "健康消费泛化，权威媒体背书是建立信任的关键",
    "智能科技需通过场景化叙事消除距离感",
    "绿色低碳正从口号转化为新能源领域的真实增长",
    "主流媒体在品牌建设中发挥凝聚共识的核心作用"
  ],
  "opening_pattern": "提问式入题 + 比喻式定义",
  "ending_pattern": "意义升华 + 品牌建议",
  "evidence_types": [
    "官方统计数据",
    "品牌合作案例",
    "营销曝光数据",
    "行业规模预测"
  ],
  "evidence_specificity_score": 85,
  "data_density_score": 65,
  "case_density_score": 90,
  "quote_density_score": 40,
  "narrative_distance": "中远景（行业观察者视角）",
  "stance_strength": "坚定",
  "sentence_rhythm": "长短句交错，排比句增强气势",
  "abstraction_level": "中等（理论提炼与案例描述并重）",
  "transferable_moves": [
    "‘趋势+案例+数据+升华’的四位一体写作模版",
    "将枯燥的预算变动比喻为‘消费心电图’的修辞法",
    "从细分行业案例中归纳普适性商业逻辑的方法"
  ],
  "anti_patterns": [
    "公关辞令堆砌（如‘艺术生活缔造者’）",
    "幸存者偏差（仅列举成功的大品牌案例）",
    "过度归因权威平台（忽略了产品力等其他变量）"
  ],
  "notable_phrases": [
    "消费心电图",
    "为心情买单",
    "科技伺候人的生活",
    "凝聚社会共识"
  ],
  "title_score": 78,
  "opening_score": 82,
  "argument_score": 75,
  "evidence_score": 88,
  "structure_score": 85,
  "style_score": 80,
  "publishability_score": 90,
  "quality_score": 76,
  "reference_value_score": 82,
  "is_activity_notice": false,
  "is_low_value": false,
  "is_advertorial": true,
  "advertorial_type": "executive_pr",
  "advertorial_confidence": 95,
  "promotional_intensity_score": 75,
  "editorial_independence_score": 40,
  "brand_exposure_level": "高",
  "source_transparency": "模糊",
  "advertorial_signals": [
    "密集列举特定媒体（总台/央视）的成功案例",
    "对合作品牌均持高度赞赏态度",
    "数据均选取曝光量、阅读量等正面公关指标",
    "结尾处带有明显的媒体平台公信力推介意图"
  ],
  "summary_200": "本文分析了2025年品牌广告预算流向揭示的四大消费趋势：情绪价值、全面健康、智能科技与绿色环保。文章通过广东文旅、茅台、海尔等标杆案例，展示了品牌如何从单一的功能宣讲转向场景化叙事与价值观共鸣。作者强调，广告预算不仅是商业选择，更是生活方式的晴雨表，并指出在当前市场环境下，借助具有公信力的权威媒体平台（如总台）进行内容共创，是品牌凝聚社会共识、走进消费者内心的关键策略。",
  "summary_500": "文章以2025年广告预算作为洞察消费市场的窗口，归纳了正在发生的四大核心趋势。首先是‘情绪价值’，旅游和文娱市场的火热促使品牌通过‘沉浸式营销’（如音乐节、嘉年华）与消费者建立情感链接。其次是‘全面健康’，健康理念已渗透至各消费环节，安利、鲁南制药等品牌通过长期绑定权威健康IP节目，利用专家背书确立专业形象。第三是‘智能科技’，家电品牌如卡萨帝、格力通过AI场景化直播，让科技参数转化为可感知的品质生活升级。第四是‘绿色环保’，新能源车企如小鹏、绿源通过综艺深度植入，将环保主张转化为具体出行体验。全文论点集中于：在消费逻辑从‘功能驱动’转向‘意义驱动’的过程中，品牌的商业表达必须依托权威平台的公信力叙事，才能转化为公共认知。文章虽然提供了丰富的行业案例和统计数据，但带有明显的品牌公关与媒体平台推介色彩，通过成功案例的堆叠证明了‘平台+内容’模式的有效性。对于营销从业者而言，本文提供了趋势分类的框架及标杆案例的打法参考，具有较高的实操借鉴价值，但需辨析其中对特定媒体平台的强偏向性。"
}
