{
  "id": "a423fde56e1e",
  "year": "2023",
  "date": "2023-11-29",
  "title": "荣耀启动上市，高端出海战略能撑起千亿市值吗？",
  "relative_path": "2023/2023-11-29_荣耀启动上市，高端出海战略能撑起千亿市值吗？.txt",
  "full_text_path": "C:\\Users\\LXG\\AI_writer\\style_corpora\\latepost\\raw_materials\\2023\\2023-11-29_荣耀启动上市，高端出海战略能撑起千亿市值吗？.txt",
  "char_count": 7586,
  "content_type": "商业评论",
  "entities": [
    "荣耀",
    "华为",
    "赵明",
    "任正非",
    "苹果",
    "三星",
    "高通",
    "Three",
    "卫讯"
  ],
  "industry": [
    "智能手机",
    "消费电子",
    "跨境电商"
  ],
  "topic": [
    "企业上市",
    "出海战略",
    "高端市场竞争",
    "折叠屏技术"
  ],
  "genre": "深度报道",
  "style": [
    "分析型",
    "叙事型"
  ],
  "audience": [
    "投资者",
    "科技行业从业者",
    "商业分析师"
  ],
  "intent": [
    "行业趋势解析",
    "企业品牌背书"
  ],
  "tone": [
    "客观",
    "前瞻性"
  ],
  "primary_question": "在独立三年并启动上市的背景下，荣耀能否通过高端出海战略和折叠屏产品支撑其资本市场的高估值？",
  "thesis_type": "战略解析型",
  "thesis_sentence": "荣耀通过在海外（尤其是欧洲）深耕高端市场、利用折叠屏技术的差异化创新挑战苹果与三星的垄断，并建立长期的渠道信任，试图复刻并超越华为当年的全球化路径。",
  "structure_pattern": "现状引入-历史回顾-区域市场深度案例-技术创新逻辑-长期主义价值观-总结愿景",
  "section_functions": [
    "背景交代：荣耀独立三周年并官宣启动上市",
    "生存回顾：海外空窗期如何通过非手机产品维系渠道火种",
    "案例分析：以香港市场为例展示高端折叠屏的突围能力",
    "产业链逻辑：分析高通与运营商为何需要荣耀作为‘第三极’",
    "产品抓手：详述折叠屏轻薄化技术的壁垒与竞争优势",
    "价值观输出：强调发达市场出海需长期积累而非性价比",
    "总结：承接华为衣钵，明确全球化高端品牌的资本路径"
  ],
  "argument_moves": [
    "通过第三方市场份额数据证明品牌的反弹生命力",
    "利用供应链巨头高通的合作姿态增强品牌高端背书",
    "通过具体产品参数（如厚度、电池容量）与三星进行硬核对比",
    "引用高管观点将‘超越华为’从口号转化为战略路径"
  ],
  "core_argument": "荣耀的资本想象力在于其能填补华为留下的高端市场空白，成为苹果、三星之外的全球化‘第三种力量’。",
  "key_points": [
    "荣耀三季度重回中国市场份额第一",
    "欧洲被定位为第二个本土市场，主攻高端而非低端",
    "折叠屏是打破直板机微创新僵局、挑战苹果三星的核心武器",
    "全产业链（运营商/芯片商）均渴望出现新的高端竞争者以制衡现有巨头",
    "海外成功无秘诀，核心资产是长期投入积累的渠道信任"
  ],
  "opening_pattern": "引用名言钩子（任正非寄语）+ 强力对比（从3%到第一的回归）。",
  "ending_pattern": "呼应开头（超越华为的价值）+ 愿景升华（撑起千亿市值的明确路径）。",
  "evidence_types": [
    "行业数据（GFK, Counterpoint）",
    "高管访谈",
    "具体渠道案例",
    "技术专利参数"
  ],
  "evidence_specificity_score": 88,
  "data_density_score": 78,
  "case_density_score": 85,
  "quote_density_score": 75,
  "narrative_distance": "中等（行业观察视角）",
  "stance_strength": "坚定（看好）",
  "sentence_rhythm": "平衡且严密，包含大量长句分析与短促的数据罗列。",
  "abstraction_level": "中等（既有宏观战略，也有微观技术细节）",
  "transferable_moves": [
    "在主攻品类缺失时，通过生态链产品维系渠道黏性的‘备胎策略’",
    "寻找产业链中‘苦巨头久矣’的生态位进行借力（如运营商制衡三星）",
    "针对高价值单一市场进行‘高举高打’的样板房建设"
  ],
  "anti_patterns": [
    "避免在品牌壁垒高的成熟市场使用性价比快钱思维",
    "避免在技术迭代期进行盲目的微创新，而应寻求形态上的代际突破"
  ],
  "notable_phrases": [
    "离婚了就不要拉拉扯扯",
    "中国荣耀不够，我们要打造世界荣耀",
    "赵明一觉醒来，门缝里又塞了一张图纸"
  ],
  "title_score": 85,
  "opening_score": 88,
  "argument_score": 82,
  "evidence_score": 86,
  "structure_score": 84,
  "style_score": 80,
  "publishability_score": 92,
  "quality_score": 87,
  "reference_value_score": 90,
  "is_activity_notice": false,
  "is_low_value": false,
  "is_advertorial": true,
  "advertorial_type": "executive_pr",
  "advertorial_confidence": 95,
  "promotional_intensity_score": 70,
  "editorial_independence_score": 45,
  "brand_exposure_level": "高",
  "source_transparency": "清晰",
  "advertorial_signals": [
    "紧扣上市新闻节点",
    "大量引用荣耀内部视角和CEO语录",
    "缺乏对地缘政治风险或专利诉讼压力的深度讨论",
    "倾向性明显的正面预期引导"
  ],
  "summary_200": "荣耀在独立三周年之际宣布启动上市，本文解析了其支撑千亿市值的逻辑。荣耀将战略核心定位于海外高端市场，试图复刻华为路径。通过在欧洲及香港市场的深耕，利用折叠屏（如Magic V2）的轻薄化差异挑战苹果和三星的统治地位。同时，利用产业链对平衡巨头势力的渴望，荣耀建立了深厚的运营商信任。文章认为，折叠屏技术与长期主义的海外渠道运营是荣耀上市估值的核心支撑。",
  "summary_500": "本文分析了荣耀（Honor）启动上市后的高端全球化战略。自2020年从华为独立以来，荣耀在中国市场实现了份额从3%到第一的绝地反弹。目前，荣耀将未来的增长重心放在海外高端市场，尤其是欧洲和香港。战略亮点包括：第一，形态突破，将折叠屏作为挑战苹果、三星垄断地位的利器，通过‘鲁班铰链’和‘青海湖电池’等自研技术，实现比竞品更轻薄的工业设计，在香港等高端市场已取得显著份额。第二，生态借力，利用运营商和芯片商（如高通）渴望出现非三星苹果‘第三极’的心理，建立深度战略合作。第三，长期主义运营，在海外曾经历30个月的新机空窗期，通过手表、笔记本等周边产品线维系品牌热度和渠道信任，不靠性价比赚快钱。文章指出，荣耀出海并非仅追求份额，而是追求单机利润更高的品牌溢价。虽然其产品和文化中仍有深厚的‘华为影子’，但荣耀正试图通过在折叠屏领域的超前迭代实现‘青出之蓝’。总结认为，荣耀能否在资本市场获得千亿估值，取决于其能否将‘中国荣耀’成功转化为‘世界荣耀’，并最终在华为无法重返的全球手机主战场上超越当年的华为。",
  "analysis_schema_version": 3
}
