{
  "analysis_schema_version": 3,
  "id": "4f67d913f90a",
  "year": "2025",
  "date": "2025-08-17",
  "title": "取消 KPI、放暑假，凯乐石从上班开始重塑品牌丨晚点周末",
  "relative_path": "2025/2025-08-17_取消 KPI、放暑假，凯乐石从上班开始重塑品牌丨晚点周末.txt",
  "full_text_path": "C:\\Users\\LXG\\AI_writer\\style_corpora\\latepost\\raw_materials\\2025\\2025-08-17_取消 KPI、放暑假，凯乐石从上班开始重塑品牌丨晚点周末.txt",
  "char_count": 9118,
  "content_type": "深度特写",
  "entities": [
    "凯乐石",
    "钟承湛",
    "晚点 LatePost",
    "朱海燕",
    "孔繁泳",
    "周子迪",
    "曾山",
    "尹乐",
    "谢卫成"
  ],
  "industry": [
    "户外运动",
    "体育用品",
    "服装零售"
  ],
  "topic": [
    "品牌重塑",
    "企业文化",
    "组织管理",
    "极致单品",
    "创始人基因"
  ],
  "genre": "商业人物特写",
  "style": [
    "叙事性",
    "硬核",
    "理想主义"
  ],
  "audience": [
    "企业管理者",
    "品牌主理人",
    "户外运动爱好者",
    "职场观察者"
  ],
  "intent": [
    "品牌公关",
    "价值观输出",
    "企业文化传播"
  ],
  "tone": [
    "热烈",
    "坦率",
    "赞赏"
  ],
  "primary_question": "一家拥有22年历史的户外品牌，如何通过将创始人的极致人格注入组织和产品，实现从传统公司向专业硬核品牌的重塑？",
  "thesis_type": "特写式论证",
  "thesis_sentence": "凯乐石通过取消KPI、给予员工运动特权、砍掉非核心SKU并深耕专业高海拔装备，成功将创始人的狂热基因转化为品牌的专业壁垒和文化符号。",
  "structure_pattern": "逻辑演进式",
  "section_functions": [
    "场景化引入：通过员工伤病与取消KPI的奇观引入凯乐石独特的组织氛围",
    "创始人画像：挖掘钟承湛截瘫后依然狂热运动的背景及其对公司的心理驱动",
    "产品战略：阐述如何通过砍掉休闲线、聚焦‘英雄产品’8000GT来实现品牌专业化转向",
    "社区与基础设施建设：回顾‘未登峰计划’和‘寻岩中国’，展现品牌在行业深耕的护城河",
    "组织管理哲学：解析取消KPI后的管理创新与研发提速",
    "总结升华：升华‘会玩’与‘创造’的关系，传递品牌精神内核"
  ],
  "argument_moves": [
    "以小见大：从办公大楼的攀岩墙细节折射品牌对运动的痴迷",
    "矛盾对比：将凯乐石‘取消KPI’与互联网大厂‘卷效率’进行对比",
    "实战背书：通过具体的秦岭救援案例证明产品的专业‘保命’性能",
    "溯源证道：通过长达19年的公益攀登项目建立品牌的专业正统性",
    "愿景感召：引用创始人带有个人英雄主义的豪言壮语（如‘装X’、‘成不了最牛运动员就做最牛公司’）"
  ],
  "core_argument": "品牌是创始人人格的延伸，真正的专业主义源于对运动本身的狂热而非对财务KPI的追逐。",
  "key_points": [
    "取消全员KPI，以‘评优’代替强制指标，激发创新张力",
    "砍掉50%SKU，撤出休闲市场，确立高海拔专业登山的定位",
    "创始人钟承湛亲自参与产品研发，定位为‘1号产品经理’",
    "长期投入非盈利的攀岩开线与未登峰计划，沉淀行业信任",
    "建立极度自由的组织氛围，如暑假、大小周、报销户外支出等"
  ],
  "opening_pattern": "奇观引入",
  "ending_pattern": "意象留白",
  "evidence_types": [
    "人物采访",
    "现场观察",
    "产品技术参数",
    "品牌历史数据",
    "救援真实案例"
  ],
  "evidence_specificity_score": 88,
  "data_density_score": 75,
  "case_density_score": 90,
  "quote_density_score": 85,
  "narrative_distance": "近距离观察",
  "stance_strength": "明确支持",
  "sentence_rhythm": "长短交错，叙述与感悟并重",
  "abstraction_level": "中低度（以具体人事物为主）",
  "transferable_moves": [
    "创始人个人魅力品牌化操作：将创始人的极限经历转化为品牌信誉",
    "极致单品驱动：打造具有极致性能的‘英雄产品’（GT系列）作为专业心智锚点",
    "垂直社群深耕：通过‘开线’、‘学校’、‘赛事’等基础设施建设垄断小众专业圈层",
    "文化赋能管理：将‘热爱’设定为招聘和考核的隐形标准，降低管理损耗"
  ],
  "anti_patterns": [
    "过度个人英雄主义：过分拔高创始人的直觉，可能掩盖了现代零售管理的逻辑",
    "散漫管理的普适性：取消KPI仅适用于高毛利/强热爱驱动行业，普通制造业需谨慎效仿",
    "软文色彩较重：部分技术细节描述带有明显的推介性质"
  ],
  "notable_phrases": [
    "成不了最牛的运动员，就做一家好玩的公司",
    "凯乐石从上班开始重塑品牌",
    "户外产品要能保命",
    "装X是内心的驱动力",
    "乱乱的也可以"
  ],
  "title_score": 92,
  "opening_score": 90,
  "argument_score": 85,
  "evidence_score": 88,
  "structure_score": 86,
  "style_score": 89,
  "publishability_score": 95,
  "quality_score": 88,
  "reference_value_score": 90,
  "is_activity_notice": false,
  "is_low_value": false,
  "is_advertorial": true,
  "advertorial_type": "brand_cooperation",
  "advertorial_confidence": 85,
  "promotional_intensity_score": 70,
  "editorial_independence_score": 60,
  "brand_exposure_level": "高",
  "source_transparency": "模糊",
  "advertorial_signals": [
    "深度解析特定系列产品（8000GT、FUGA）的技术参数及演进",
    "对品牌多位高管及创始人进行了详尽且正向的特写报道",
    "文章末尾附带品牌背景说明与合作栏目介绍",
    "披露品牌线下店开店数量等商业利好信息"
  ],
  "summary_200": "本文深度剖析了中国户外品牌凯乐石的重塑之路。创始人钟承湛因事故截瘫后，将对极限运动的狂热注入品牌。凯乐石采取了‘非典型’管理：取消KPI、发放户外假期、将总部打造为攀岩场。战略上，砍掉休闲产品聚焦专业硬核装备，打造出能‘保命’的英雄单品。通过长期赞助‘未登峰计划’和‘寻岩中国’，品牌建立了深厚行业护城河。这种以热爱驱动创新的组织模式，使老品牌实现了年轻化与专业化的双重跃迁。",
  "summary_500": "这篇来自《晚点周末》的深度特写，探讨了凯乐石（Kailas）如何通过创始人人格化的方式重塑品牌调性。文章首先以其独特的办公文化切入——员工可以在办公室攀岩下班，且全员取消了KPI，取而代之的是对户外运动的极致鼓励。这种管理理念源自创始人钟承湛，一个即便高位截瘫也要继续滑雪骑摩托的‘运动狂人’。文章详述了凯乐石的专业化转型历程：2019年后，公司毅然砍掉盈利的休闲SKU，转而全力投入8000GT高海拔羽绒服等‘英雄产品’的研发。钟承湛作为‘1号产品经理’，通过对空气梭织法等技术细节的痴迷，确保了产品的极高性能。同时，凯乐石通过长达19年的‘未登峰计划’和大规模的‘寻岩中国’开线活动，深耕户外基础设施，不仅为行业输送了安全标准，更在专业核心圈层建立了无可撼动的正统地位。在组织上，凯乐石引入了安踏背景的职业经理人弥补运营短板，同时保持了不卷效率、尊重创新的‘放假文化’。文章认为，凯乐石的成功在于其并非简单售卖商品，而是通过组织文化和产品研发的合一，输出了一种极具辨识度的生活哲学。虽然带有一定的品牌合作色彩，但其在品牌心智构建和创始人基因传递方面的案例极具参考价值。"
}
