{
  "id": "eecd2a859ffc",
  "year": "2021",
  "date": "2021-05-14",
  "title": "《至高忠诚》：一个出色的领导者，应该具有什么样的品质？",
  "relative_path": "2021/2021-05-14_《至高忠诚》：一个出色的领导者，应该具有什么样的品质？.txt",
  "full_text_path": "C:\\Users\\LXG\\AI_writer\\raw_materials\\2021\\2021-05-14_《至高忠诚》：一个出色的领导者，应该具有什么样的品质？.txt",
  "char_count": 4154,
  "content_type": "书评",
  "industry": [
    "公共管理",
    "管理咨询",
    "出版业"
  ],
  "topic": [
    "领导力",
    "政治哲学",
    "职业道德",
    "组织行为学"
  ],
  "genre": "深度报道",
  "style": [
    "叙事性",
    "评论性",
    "人文性"
  ],
  "audience": [
    "中高层管理者",
    "政治学爱好者",
    "职场精英"
  ],
  "intent": [
    "启发思考",
    "知识传播",
    "品牌背书"
  ],
  "tone": [
    "理智",
    "审慎",
    "批判性"
  ],
  "primary_question": "在复杂的权力博弈与职业压力中，出色的领导者应具备何种核心品质，以及如何区分“盲目忠诚”与“诚实忠诚”？",
  "thesis_type": "诠释型",
  "thesis_sentence": "真正的领导力源于自信与谦逊的平衡，它要求的不是对个人的绝对服从，而是基于真相与正直的“诚实的忠诚”。",
  "structure_pattern": "叙议结合式",
  "section_functions": [
    "引入背景：通过2016年美大选关键节点勾画戏剧冲突",
    "核心冲突：复现“忠诚晚餐”细节，确立全书叙事基调",
    "理论对比：通过特朗普与前任总统的对比，界定管理风格的本质差异",
    "反面案例：分析朱利安尼的独裁风格及其对组织的负面影响",
    "正面驱动：阐述海伦·费伊与科米妻子对其价值观的重塑",
    "文化升华：将案例提升至儒家哲学与制度保障的高度"
  ],
  "argument_moves": [
    "场景还原法：通过菜单、对话等细节增强叙事可信度",
    "定义辨析法：将“忠诚”细分为“黑帮式顺从”与“诚实的忠诚”",
    "人物对比法：利用三位领导者的不同风格构建领导力光谱",
    "跨文化联结：将西方政治冲突与中国传统政治伦理（如谏官制度）进行类比"
  ],
  "core_argument": "领导者若缺乏谦逊与自知之明，便会通过恐惧而非真相进行领导；组织的长久健康依赖于保障成员说真话的制度与道德底线。",
  "key_points": [
    "黑帮式领导依靠权力和恐惧要求下属效忠，而优秀领导者通过谦逊吸引人才",
    "诚实是更高层面的忠诚，它是做决策时防止被蒙蔽的关键",
    "自信的领导者会通过成就团队来照亮自我，而非压制他人获取关注",
    "推己及人的共情能力是公共事业与司法正义的底层逻辑",
    "新闻自由与制度约束是保障“真话”能够被表达的外在必要条件"
  ],
  "opening_pattern": "时事新闻钩子",
  "ending_pattern": "哲学思考与制度反思",
  "evidence_types": [
    "个人回忆录细节",
    "历史政治事件",
    "对比案例",
    "名言引用"
  ],
  "evidence_specificity_score": 88,
  "data_density_score": 30,
  "case_density_score": 85,
  "quote_density_score": 70,
  "narrative_distance": "中近景（带有强烈主观观察的叙事）",
  "stance_strength": "明确",
  "sentence_rhythm": "长短交错，叙述平实但逻辑转折紧凑",
  "abstraction_level": "中等（从具体晚餐场景上升到领导力哲学）",
  "transferable_moves": [
    "利用核心冲突场景（如尴尬的晚餐）作为叙事锚点，以此引出深层次的价值观辩论",
    "通过对反面典型（朱利安尼）的深刻剖析，反向定义正面标准的必要性",
    "将个人成长中的女性影响视角引入传统宏大叙事，增加内容的温情度与多维视角"
  ],
  "anti_patterns": [
    "避免空洞的口号化赞美，通过具体的行为细节（如不倾听别人、自顾自讲话）展现人物缺失",
    "避免将领导力局限于职场，将其延伸至家庭与社会正义，提升论点厚度"
  ],
  "notable_phrases": [
    "诚实的忠诚",
    "挡在鲁迪与话筒之间",
    "在团队的成绩中显得熠熠生辉",
    "抚平创伤，缓解痛苦，让他人免受你曾经遭受的苦难"
  ],
  "title_score": 82,
  "opening_score": 85,
  "argument_score": 88,
  "evidence_score": 90,
  "structure_score": 86,
  "style_score": 84,
  "publishability_score": 92,
  "quality_score": 89,
  "reference_value_score": 87,
  "is_activity_notice": false,
  "is_low_value": false,
  "summary_200": "本文是对前FBI局长詹姆斯·科米自传《至高忠诚》的深度解读。文章以科米与特朗普关于“忠诚”的博弈为切入点，剖析了领导力中的关键品质：自信、谦逊与正直。通过对比特朗普的黑帮式领导风格与奥巴马等人的职业素养，并结合科米职业生涯中深受朱利安尼、海伦·费伊及妻子帕特里斯影响的往事，论证了“诚实”才是最高层面的忠诚，强调了说真话的制度保障与道德自觉对组织及社会的重要性。",
  "summary_500": "这篇文章通过解构詹姆斯·科米的回忆录，探讨了权力和领导力的本质。核心情节围绕2017年特朗普与科米在白宫的那场“尴尬晚餐”展开，揭示了特朗普要求的“盲目效忠”与科米坚持的“基于真相的诚实”之间的根本对立。作者借此引出领导力的定义：真正的领导者应具备谦逊和自知之明，而非依靠恐惧统治。文章进一步追溯了科米的价值溯源：他在政坛强人朱利安尼身上看到了独裁与缺乏谦逊如何导致信息闭塞；在海伦·费伊身上看到了优秀领导者通过成就下属来提升团队的智慧；在妻子帕特里斯处理丧子之痛的过程中，体悟到了将个人苦难转化为社会正义的推己及人。文章后半部分将这种西方政治博弈引入到中国传统儒家视野下，对比了“从谏如流”与“虚怀若谷”的政治理想，指出防止权力贪恋的答案在于：一方面重申谦逊与诚实的道德原则，另一方面利用新闻自由等制度保障说真话的权利。全文逻辑严密，叙事生动，将一本政治人物传记升华为关于职业操守与组织文化的深度思考，不仅具有很强的可读性，也为现代管理者提供了极具参考价值的道德坐标。"
}
