{
  "id": "7456b2d502ac",
  "year": "2023",
  "date": "2023-03-06",
  "title": "什么样的组织才能实现可持续创新？",
  "relative_path": "2023/2023-03-06_什么样的组织才能实现可持续创新？.txt",
  "full_text_path": "C:\\Users\\LXG\\BizCase\\raw_materials\\2023\\2023-03-06_什么样的组织才能实现可持续创新？.txt",
  "char_count": 5092,
  "industry": [
    "企业管理",
    "商业模式",
    "组织行为学",
    "科技创新"
  ],
  "topic": [
    "可持续创新",
    "元组织",
    "组织能力",
    "管理学新概念"
  ],
  "genre": "深度分析文章",
  "style": [
    "学术性",
    "理论探讨",
    "案例分析"
  ],
  "audience": [
    "企业管理者",
    "战略规划者",
    "商业研究者",
    "对组织创新感兴趣的人群"
  ],
  "intent": [
    "普及知识",
    "提供洞见",
    "启发思考",
    "案例借鉴"
  ],
  "tone": [
    "专业",
    "客观",
    "探讨性",
    "前瞻性"
  ],
  "structure_pattern": "总-分-总",
  "core_argument": "传统中心化、层级制组织难以实现可持续优质创新，而具备去中心化、开放、包容、交互机制的“元组织”通过其六大核心能力（预测、适应、反思、响应、包容、责任感）能够更好地实现可持续创新，并且可以通过组织改造和实践来实现。",
  "key_points": [
    "“元组织”是具有去中心化、开放、包容、良好交互机制的自管理组织生态系统。",
    "可持续优质创新（ESG导向）是当前时代的需求，区别于可能带来负面效应的传统创新。",
    "传统中心化、层级制组织在VUCA时代难以实现可持续优质创新。",
    "元组织通过吸纳多元主体、共同价值理念、透明开放的交互机制实现整体可持续发展。",
    "元组织具备实现可持续创新所需的六大能力：预测、适应、反思、响应、包容、责任感。",
    "元组织可以通过组织改造实现，文中以Zappos和晨星公司为例。",
    "元组织建设可以跨越行业和规模，甚至可以构建大规模的跨区域零售业元组织。"
  ],
  "opening_pattern": "提出问题引入概念",
  "ending_pattern": "总结论点并展望实践",
  "notable_phrases": [
    "元组织",
    "可持续优质创新",
    "VUCA时代",
    "去中心化",
    "开放",
    "包容",
    "交互机制",
    "六大能力",
    "六边形创新战士",
    "合弄制",
    "晨星公司（Morning Star）",
    "CLOU（colleague letter of understanding）"
  ],
  "quality_score": 85,
  "reference_value_score": 88,
  "is_activity_notice": false,
  "is_low_value": false,
  "summary_200": "本文探讨了实现可持续创新的组织模式。作者指出，在VUCA时代，传统中心化、层级制组织难以应对风险和变化，无法有效实现可持续优质创新。文章引入“元组织”概念，将其定义为去中心化、开放、包容、具备良好交互机制的自管理组织生态系统，成员可包含企业、政府、个人等多元主体，共同追求可持续发展目标。元组织具备预测、适应、反思、响应、包容和责任感六大核心能力，使其在创新方面优于传统组织。文章通过Zappos公司改造为合弄制以及晨星公司的自管理模式，阐述了元组织的实践路径，并提及了大规模零售业元组织的建设尝试，强调了组织向元组织转型对于激发创新、实现可持续发展的战略意义。",
  "summary_500": "本文深入探讨了在当前复杂多变的VUCA时代，什么样的组织能够成功实现可持续创新。文章首先指出，创新对社会发展至关重要，但并非所有创新都具有积极意义，尤其是在ESG（环境、社会与公司治理）日益受到重视的背景下，对环境友好、对社会有益的可持续优质创新（sustainable innovations）成为时代发展的必然需求。作者旗帜鲜明地提出，传统的中心化、层级制组织由于其固有的僵化结构和应对风险的能力不足，将难以在快速变化的环境中实现可持续创新，甚至只能勉强维持现有业绩。\n\n在此基础上，文章隆重推出“元组织”这一管理学新概念。元组织被定义为一个由多元主体构成的组织生态系统，其核心特征是去中心化、开放、包容以及良好的交互机制。它超越了传统以单一企业为单位的模式，能够整合企业、政府机构、民间组织、企业家、消费者等不同主体，在共同的价值理念和发展目标驱动下，形成透明、开放的沟通与合作机制，从而激发集体智慧，实现共同创新。与只关注自身利益的传统组织不同，元组织旨在激发各成员创造既有利于自身也有利于整体的创新，最终实现整体的可持续发展。\n\n文章详细阐述了元组织之所以能够实现可持续创新的关键在于其具备传统组织所不具备的六大核心能力：1. 预测能力（anticipation of risks），能够敏锐感知并预判外部环境变化和潜在风险；2. 适应能力（resilience），通过去中心化网状架构和集体学习机制快速应对环境变化；3. 反思能力（reflexivity），能够高效复盘纠偏，避免错误方向的累积；4. 响应能力（responsiveness），能够快速而敏捷地抓住外部机会；5. 包容力（inclusion），能够融合多元观点，促进创新思维的碰撞；6. 责任感（accountability），激发成员创造力，并强化社会主体意识。凡是具备这六大能力的组织，无论大小，都可归类为元组织的范畴。\n\n为了论证元组织的可行性，文章列举了多个实践案例。亚马逊旗下的Zappos通过将组织结构改造为高度自管理的合弄制（Holacracy），成功实现了规模扩大后的高效协作与持续创新。传统行业中的番茄加工商晨星公司（Morning Star）自创立之初就坚持自管理组织模式，通过“同事间理解信”（CLOU）机制，实现了大规模传统企业的成功管理。此外，文章还提到一个正在进行的、规模庞大的跨区域零售业元组织建设，旨在通过技术共享与整合，全面升级实体零售业的客户体验和创新能力。文章最后总结，通过组织改造，具备这六大能力的元组织将成为激发可持续创新、实现组织韧性的强大力量。"
}
