{
  "id": "87cbe79bc931",
  "year": "2023",
  "date": "2023-07-27",
  "title": "数字时代的知识与批判丨FBK翻书日签 2023年7月27日",
  "relative_path": "2023/2023-07-27_数字时代的知识与批判丨FBK翻书日签 2023年7月27日.txt",
  "full_text_path": "C:\\Users\\LXG\\BizCase\\raw_materials\\2023\\2023-07-27_数字时代的知识与批判丨FBK翻书日签 2023年7月27日.txt",
  "char_count": 364,
  "industry": [
    "互联网",
    "文化艺术",
    "科技"
  ],
  "topic": [
    "数字时代",
    "知识获取",
    "批判性思维"
  ],
  "genre": "日签/短讯",
  "style": [
    "信息提示",
    "引用"
  ],
  "audience": [
    "对数字时代信息敏感者",
    "知识工作者",
    "学生"
  ],
  "intent": [
    "提供信息",
    "引导思考"
  ],
  "tone": [
    "中性",
    "启发性"
  ],
  "structure_pattern": "标题 - 日期 - 链接 - 来源模式 - 正文（图片搜索提示）",
  "core_argument": "文章本身未提供核心论点，仅为链接和图片搜索提示。",
  "key_points": [
    "文章发布于2023年7月27日，标题为“数字时代的知识与批判”。",
    "提供了一个微信公众号文章链接。",
    "该页面触发了全局图片搜索，找到1张图片。"
  ],
  "opening_pattern": "标题和日期",
  "ending_pattern": "图片搜索结果提示",
  "notable_phrases": [
    "数字时代的知识与批判",
    "FBK翻书日签",
    "此页面触发全局图片搜索模式"
  ],
  "quality_score": 25.5,
  "reference_value_score": 15,
  "is_activity_notice": false,
  "is_low_value": true,
  "summary_200": "该内容为一条微信公众号的日签信息，发布于2023年7月27日，标题为“数字时代的知识与批判”。内容主体为一个微信文章链接，并在末尾提示该页面触发了全局图片搜索模式，共找到1张图片。文章本身未提供实质性内容，信息密度极低，主要作用是导向一个外部链接。",
  "summary_500": "这是一篇发布于2023年7月27日的微信公众号日签内容，标题为“数字时代的知识与批判”。文章的正文部分非常简短，主要包含了一个指向微信文章的链接，以及一个关于图片搜索结果的提示信息，表明该页面触发了全局图片搜索，并找到了1张图片。文章的结构模式为“标题 - 日期 - 链接 - 来源模式 - 正文（图片搜索提示）”。  从内容上看，它并未展开关于“数字时代知识与批判”的讨论，而是将核心信息隐藏在了外部链接中。因此，其核心论点和关键要点都依赖于用户点击链接进行进一步探索。  其风格可以归类为信息提示和引用，受众定位可能是对数字时代信息敏感、知识工作者或学生等群体，意图在于提供信息和引导思考，但内容本身并未直接实现。语气中性且略带启发性。  由于文章内容本身非常简短，信息密度低，缺乏实质性论述，主要价值体现在其提供的链接，因此其质量得分和参考价值得分较低。它不是一个活动通知，但可以被视为低价值内容，因为其直接提供的信息量非常有限。"
}
