{
  "id": "5550d753003f",
  "year": "2023",
  "date": "2023-08-11",
  "title": "社会创新的力量丨FBK翻书日签 2023年8月11日",
  "relative_path": "2023/2023-08-11_社会创新的力量丨FBK翻书日签 2023年8月11日.txt",
  "full_text_path": "C:\\Users\\LXG\\AI_writer\\raw_materials\\2023\\2023-08-11_社会创新的力量丨FBK翻书日签 2023年8月11日.txt",
  "char_count": 355,
  "content_type": "每日日签",
  "industry": [
    "社会创新",
    "公益"
  ],
  "topic": [
    "社会创新",
    "个人成长"
  ],
  "genre": "碎片化内容",
  "style": [
    "极简",
    "励志"
  ],
  "audience": [
    "社会创新从业者",
    "职场人士",
    "阅读爱好者"
  ],
  "intent": [
    "品牌露出",
    "理念传播"
  ],
  "tone": [
    "严肃",
    "正向"
  ],
  "primary_question": "什么是社会创新的力量？",
  "thesis_type": "感悟式",
  "thesis_sentence": "社会创新通过日常的思考与积累产生改变现状的力量。",
  "structure_pattern": "标题+日期+核心引言（推测）",
  "section_functions": [
    "标题界定主题",
    "日期标记时效",
    "日签主体传达金句"
  ],
  "argument_moves": [
    "直接引用名言或观点",
    "通过视觉化卡片增强仪式感"
  ],
  "core_argument": "社会创新需要持续的关注与思想积累，日签作为载体提供了每日思考的锚点。",
  "key_points": [
    "强调社会创新的力量",
    "建立每日阅读的仪式感"
  ],
  "opening_pattern": "直叙式标题",
  "ending_pattern": "标准化落款",
  "evidence_types": [
    "名言警句"
  ],
  "evidence_specificity_score": 10,
  "data_density_score": 5,
  "case_density_score": 0,
  "quote_density_score": 90,
  "narrative_distance": "旁观者",
  "stance_strength": "中等",
  "sentence_rhythm": "极简",
  "abstraction_level": "高",
  "transferable_moves": [
    "使用“日签”形式进行低成本、高频次的品牌触达",
    "利用固定栏目（FBK翻书日签）培养用户期待感"
  ],
  "anti_patterns": [
    "内容极其单薄，缺乏深度论述",
    "过度依赖图片视觉而忽视文字信息密度"
  ],
  "notable_phrases": [
    "社会创新的力量"
  ],
  "title_score": 40,
  "opening_score": 20,
  "argument_score": 15,
  "evidence_score": 10,
  "structure_score": 30,
  "style_score": 40,
  "publishability_score": 30,
  "quality_score": 20,
  "reference_value_score": 15,
  "is_activity_notice": false,
  "is_low_value": true,
  "summary_200": "该内容为“FBK翻书”栏目的每日日签，发布于2023年8月11日。其核心价值在于通过极简的形式（标题+日期+引言图片）向用户传递关于“社会创新力量”的启示。由于正文缺乏具体的论证过程、案例支撑或深度解读，其信息密度极低，主要起到品牌日常打卡和简单理念输出的作用，对于需要深入学习和RAG写作的参考价值有限。",
  "summary_500": "本篇内容属于社交媒体中常见的碎片化“日签”类型。文章标题为《社会创新的力量丨FBK翻书日签 2023年8月11日》，其核心结构由主题名称、品牌标识和发布日期组成。从内容分析来看，这并非一篇完整的议论文或深度报道，而是一个典型的品牌触达工具，旨在通过每日更新的名言或简短感悟，在潜在读者心中建立“社会创新”的价值观链接。在写作机制上，它采用了极简主义风格，摒弃了复杂的逻辑推导，直接给出结论或启发性话语。这种模式的优点是易于传播、阅读门槛极低，能有效利用读者的碎片化时间进行品牌心智占领；但其缺点也十分明显，即信息承载量极小，缺乏必要的证据支持（Evidence）和动作指南（Actionable moves）。对于专业分析者而言，该内容的参考价值主要体现在其运营模式上——即如何利用“翻书日签”这一栏目化产品进行低成本的内容生产与社群触达。在内容质量评分方面，由于正文信息极度匮乏，其在论证、证据、结构等维度得分均较低，被标记为低价值/信息过短的文章。"
}
