{
  "id": "e41ad760bc15",
  "year": "2023",
  "date": "2023-05-31",
  "title": "未来的冲击丨FBK翻书日签 2023年5月31日",
  "relative_path": "2023/2023-05-31_未来的冲击丨FBK翻书日签 2023年5月31日.txt",
  "full_text_path": "C:\\Users\\LXG\\BizCase\\raw_materials\\2023\\2023-05-31_未来的冲击丨FBK翻书日签 2023年5月31日.txt",
  "char_count": 359,
  "industry": [
    "互联网"
  ],
  "topic": [
    "科技前沿",
    "人工智能"
  ],
  "genre": "日签",
  "style": [
    "信息聚合",
    "摘要"
  ],
  "audience": [
    "科技爱好者",
    "AI从业者"
  ],
  "intent": [
    "信息传播",
    "观点分享"
  ],
  "tone": [
    "客观"
  ],
  "structure_pattern": "标题-日期-链接-来源-正文",
  "core_argument": "文章主要内容缺失，仅为日签标题和链接信息。",
  "key_points": [
    "日签标题：未来的冲击",
    "日期：2023年5月31日",
    "来源：wechat_fallback_global",
    "内容提示：触发全局图片搜索模式，找到1张图片。"
  ],
  "opening_pattern": "标题-日期",
  "ending_pattern": "图片搜索结果说明",
  "notable_phrases": [
    "未来的冲击",
    "FBK翻书日签"
  ],
  "quality_score": 10,
  "reference_value_score": 5,
  "is_activity_notice": false,
  "is_low_value": true,
  "summary_200": "本文为FBK翻书日签2023年5月31日的微信推文链接。日签标题为“未来的冲击”。文章正文信息非常简略，仅包含日期、原始链接、来源模式（wechat_fallback_global）以及一条关于触发全局图片搜索并找到一张图片的说明。原文内容密度极低，缺乏实质性信息。",
  "summary_500": "这是一篇发布于2023年5月31日的“FBK翻书日签”内容，标题为“未来的冲击”。文章主体由标题、日期、原始微信文章链接、来源标识（wechat_fallback_global）以及一句说明组成。该说明指出，该页面触发了全局图片搜索模式，共找到1张图片。除此以外，文章正文中未包含任何关于“未来的冲击”这一主题的实质性论述、分析或信息。内容价值极低，主要起到了一个链接指向和基本信息提示的作用，不具备深入的参考价值和信息密度。"
}
