{
  "id": "eedd5ecf71c1",
  "year": "2023",
  "date": "2023-09-15",
  "title": "陆雄文：除了产品和技术，企业还需注重“管理出海”",
  "relative_path": "2023/2023-09-15_陆雄文：除了产品和技术，企业还需注重“管理出海”.txt",
  "full_text_path": "C:\\Users\\LXG\\BizCase\\raw_materials\\2023\\2023-09-15_陆雄文：除了产品和技术，企业还需注重“管理出海”.txt",
  "char_count": 3723,
  "industry": [
    "消费品",
    "汽车",
    "科技"
  ],
  "topic": [
    "企业出海",
    "品牌国际化",
    "管理出海",
    "中国品牌"
  ],
  "genre": "商业评论",
  "style": [
    "分析性",
    "观点性",
    "指导性"
  ],
  "audience": [
    "企业管理者",
    "国际业务从业者",
    "品牌营销人员",
    "对中国品牌出海感兴趣的读者"
  ],
  "intent": [
    "信息分享",
    "观点阐述",
    "策略指导",
    "趋势分析"
  ],
  "tone": [
    "专业",
    "深刻",
    "前瞻",
    "建议性"
  ],
  "structure_pattern": "总分总-多角度分析",
  "core_argument": "中国企业出海不仅要关注产品和技术，更需注重管理、服务、文化融合及本地化，实现从‘走出去’到‘走进去’的深度战略转型。",
  "key_points": [
    "一流品牌需配套一流服务，企业出海应注重管理出海（供应链、资金、人力资源等）。",
    "‘中国制造’与‘中国品牌’并非对立，而是融合共生，品牌是高质量发展象征。",
    "海外消费者对‘中国品牌’印象已高于‘中国制造’，科技创新驱动品牌影响力提升。",
    "中国企业出海在服务、文化建设、营销策略方面存在短板，需融入本地文化，讲好品牌故事。",
    "新一代出海企业拥有更丰富的跨境电商和社交媒体平台，但线下渠道和本土化仍是关键。",
    "企业出海经历‘走出去’（产品贸易）和‘走进去’（本地投资建厂、研发等），后者要求更高。",
    "‘走进去’需突破重点市场、做好技术攻关与知识产权保护、抱团发展并融入当地。",
    "国际化人才队伍的建设是企业出海（尤其‘走进去’阶段）的主要短板。"
  ],
  "opening_pattern": "以近期热点事件（茅台与瑞幸联名）引入，引出品牌转型和新消费趋势，为后续讨论铺垫。",
  "ending_pattern": "总结“走进去”战略的关键要素（市场、技术、人才、融合），并强调人才梯队建设的重要性，文章最后附带了转载信息和相关内容推荐。",
  "notable_phrases": [
    "管理出海",
    "中国制造”与“中国品牌”并非低端与高级、落后与先进的对比，而是融合共生的一体",
    "品牌是高质量发展的重要象征",
    "一流产品要配套一流服务",
    "中国品牌在服务提供、文化建设、营销策略等方面仍存短板有待补齐",
    "新一代出海的企业拥有更为丰富的跨境电商和社交媒体平台",
    "坚守品牌价值观并融入本地文化、讲好品牌故事",
    "从“走出去”到“走进去”",
    "国际化人才队伍的数量和质量是中国企业出海的主要短板",
    "抱团发展，更要融入当地"
  ],
  "quality_score": 85,
  "reference_value_score": 88,
  "is_activity_notice": false,
  "is_low_value": false,
  "summary_200": "本文由复旦大学管理学院院长陆雄文撰写，指出中国企业在产品和技术出海的同时，更需重视“管理出海”。文章强调“中国制造”与“中国品牌”的融合共生关系，认为品牌是高质量发展的象征。作者分析了中国品牌在海外的进步，但也指出了在服务、文化融合、营销策略方面的短板。文章进一步探讨了企业从“走出去”到“走进去”的战略转型，提出在重点市场选择、技术攻关、知识产权保护、人才队伍建设以及融入当地等方面需重点关注，并强调了本土化人才的重要性。",
  "summary_500": "复旦大学管理学院院长陆雄文在题为“陆雄文：除了产品和技术，企业还需注重‘管理出海’”的文章中，深度剖析了中国企业在全球化进程中的战略升级。文章以近期“酱香拿铁”等热点事件为例，引出了传统品牌寻求转型与新消费趋势的结合，并强调了“中国制造”向“中国智造”的演进，以及“中国品牌”在全球市场日益增长的影响力。陆雄文院长提出，一流的品牌不仅需要一流的产品支撑，更需要配套一流的服务，而对于中国企业而言，“管理出海”是关键一环，这包括提升全球供应链管理、资金保障、人力资源管理能力，以及可持续发展的价值观，并需结合当地市场特点进行提升和融合。文章明确指出，“中国制造”与“中国品牌”并非低端与高级的对立，而是融合共生的关系，品牌代表着企业的形象、信誉和价值，是高质量发展的重要体现。在海外市场，中国新能源汽车等领域的成功出海被视为科技创新和品牌影响力提升的典范。然而，作者也坦诚地指出了中国品牌在服务提供、文化建设和营销策略方面存在的短板，尤其强调了坚守品牌价值观、融入本地文化、讲好品牌故事的重要性，认为“有灵魂的品牌”才能赢得海外消费者的尊重。文章进一步区分了企业出海的“走出去”（以产品贸易为主）和“走进去”（在当地投资建厂、设研发中心等）两种模式，指出“走进去”对企业能力提出了更高要求。在“走进去”的过程中，企业需要突破重点市场、做好技术攻关与知识产权先行、抱团发展并高度融入当地。陆院长特别强调，国际化人才队伍的数量和质量是中国企业出海的主要短板，企业在制定“走进去”战略时，必须重点考虑海外人才梯队的建设。文章整体展现了对中国企业国际化战略的深刻洞察和前瞻性指导。"
}
