{
  "id": "7da5bbd1ba0c",
  "year": "2024",
  "date": "2024-09-25",
  "title": "引领数字时代的生态型商业模式",
  "relative_path": "2024/2024-09-25_引领数字时代的生态型商业模式.txt",
  "full_text_path": "C:\\Users\\LXG\\AI_writer\\raw_materials\\2024\\2024-09-25_引领数字时代的生态型商业模式.txt",
  "char_count": 7911,
  "content_type": "学术综述",
  "industry": [
    "数字经济",
    "互联网",
    "战略管理"
  ],
  "topic": [
    "商业模式创新",
    "商业生态系统",
    "组织双元性",
    "数字化转型"
  ],
  "genre": "理论研究",
  "style": [
    "学术化",
    "结构化",
    "严谨"
  ],
  "audience": [
    "企业高管",
    "商业研究者",
    "管理咨询师"
  ],
  "intent": [
    "理论框架构建",
    "知识传播",
    "趋势导引"
  ],
  "tone": [
    "客观",
    "权威",
    "前瞻"
  ],
  "primary_question": "在数字技术迭代加速的背景下，传统的商业模式理论如何演进为适应生态化竞争的新型框架？",
  "thesis_type": "概念框架提出",
  "thesis_sentence": "文章提出从传统4V框架（价值主张、创造、交付、捕获）向包含共同演化愿景、价值共创、价值共获及泛社区网络的“4co-生态型商业模式（4co-EBM）”转型。",
  "structure_pattern": "演进对比式",
  "section_functions": [
    "研究背景与文献计量分析方法说明",
    "生态导向下的商业模式发展趋势阐述",
    "传统4V框架的历史回顾与局限分析",
    "商业模式创新的动态特征与开放式创新理论引入",
    "标杆企业案例验证（字节跳动、华为、亚马逊）",
    "4co-生态型商业模式的定义与未来展望"
  ],
  "argument_moves": [
    "通过大数据文献筛选识别研究热点",
    "对比传统模式与生态模式的构成维度差异",
    "引入组织双元性解释企业在变化中的适应性",
    "利用头部企业实践证明数字技术的协同效应",
    "界定生态型商业模式作为‘商业模式的集成’的终极形态"
  ],
  "core_argument": "数字时代的商业模式已由单一企业的内部闭环演变为利益共同体的可协同、可演化的集成系统，其核心在于利用数字技术强化网络效应与生态韧性。",
  "key_points": [
    "商业模式研究重点正从企业内部创新向外部动态扩张转移",
    "4co框架包含：共同演化愿景、价值共创、价值共获、泛社区网络",
    "组织双元性是实现短期敏捷性与长期适应性的核心能力",
    "数字技术通过降低生产成本和提高双向互动，重塑了价值链",
    "未来的商业模式是‘商业模式的商业模式’，侧重整体利润而非单一节点盈利"
  ],
  "opening_pattern": "背景铺垫与问题识别",
  "ending_pattern": "愿景描绘与核心定义总结",
  "evidence_types": [
    "文献计量学数据 (Citespace分析)",
    "理论引用 (开放式创新、组织双元性)",
    "企业案例 (字节跳动、华为、亚马逊、爱彼迎)"
  ],
  "evidence_specificity_score": 85,
  "data_density_score": 75,
  "case_density_score": 80,
  "quote_density_score": 70,
  "narrative_distance": "远景观察",
  "stance_strength": "坚定",
  "sentence_rhythm": "长短句交替，以稳重学术长句为主",
  "abstraction_level": "高",
  "transferable_moves": [
    "使用‘4co’维度评估现有业务的生态化程度",
    "应用‘组织双元性’概念平衡企业的探索与利用活动",
    "借鉴字节跳动的‘底层数据技术迁移’战略进行业务扩张",
    "从‘网络效应、集聚能力、去中介化风险、抗风险能力、桥接性’五个维度评估平台韧性"
  ],
  "anti_patterns": [
    "封闭式孤立创新模式",
    "忽视外部价值共创者的单一价值捕获",
    "缺乏动态调整能力的僵化组织结构"
  ],
  "notable_phrases": [
    "4co-生态型商业模式",
    "组织双元性",
    "商业模式的商业模式",
    "泛社区网络"
  ],
  "title_score": 82,
  "opening_score": 78,
  "argument_score": 92,
  "evidence_score": 88,
  "structure_score": 90,
  "style_score": 85,
  "publishability_score": 90,
  "quality_score": 89,
  "reference_value_score": 95,
  "is_activity_notice": false,
  "is_low_value": false,
  "summary_200": "本文系统论述了数字时代商业模式从传统4V框架向“4co-生态型商业模式”的演进。作者通过文献计量分析指出，商业模式创新已呈现动态化、数字化、生态化特征。核心观点包括：企业需具备组织双元性以平衡内部效率与外部扩张；利用数字技术构建由共同演化愿景、价值共创、价值共获及泛社区网络组成的生态系统。文章结合字节跳动、华为等案例，强调未来商业模式是多个模式的集成，旨在通过生态协同实现整体增长。",
  "summary_500": "这篇文章由清华大学、安徽财经大学及伯明翰大学的多位学者共同撰写，深度解析了数字革命背景下商业模式创新的范式转移。研究首先通过对Web of Science数据库中237篇核心文献的深度内容分析，揭示了商业模式研究从战略管理向企业创新与商业生态系统（BE）融合的趋势。文章对比了传统商业模式的“4V”框架（价值主张、创造、交付、获取），指出其在应对外部动态环境和利用数字红利方面的不足，进而提出了“4co-生态型商业模式（4co-EBM）”概念。该框架由四个关键维度组成：共同演化愿景（Co-design）、价值共创（Co-creation）、价值共获（Co-capture）以及泛社区网络（Community）。\n\n文章重点讨论了商业模式创新的动态特征，引入了“开放式创新”和“组织双元性”理论，强调企业必须同时具备敏捷的外部探索能力和高效的内部利用能力。在实证层面，文章通过字节跳动如何将底层个性化推荐技术跨产品迁移，以及华为在外部制裁下通过技术迭代实现终端业务回归的案例，验证了生态型模式的韧性。最后，作者提出未来商业模式应是“商业模式的集成”，其成功不再取决于单一业务的盈利，而取决于整个生态系统的可协同性、演化能力及对去中介化风险的抵御。该研究为高科技和平台型企业提供了重要的战略管理参考。"
}
