{
  "id": "b162d6340313",
  "year": "2024",
  "date": "2024-02-26",
  "title": "齐美尔论社交丨FBK翻书日签 2024年2月26日",
  "relative_path": "2024/2024-02-26_齐美尔论社交丨FBK翻书日签 2024年2月26日.txt",
  "full_text_path": "C:\\Users\\LXG\\AI_writer\\raw_materials\\2024\\2024-02-26_齐美尔论社交丨FBK翻书日签 2024年2月26日.txt",
  "char_count": 354,
  "content_type": "社交媒体日签",
  "industry": [
    "人文学术",
    "社会科学"
  ],
  "topic": [
    "齐美尔",
    "社交理论",
    "社会学"
  ],
  "genre": "摘录",
  "style": [
    "极简",
    "碎片化"
  ],
  "audience": [
    "社会学研究者",
    "哲学爱好者",
    "知识精英"
  ],
  "intent": [
    "品牌维护",
    "知识传播"
  ],
  "tone": [
    "学术",
    "沉稳"
  ],
  "primary_question": "齐美尔如何定义社交的本质？",
  "thesis_type": "观点陈述型",
  "thesis_sentence": "文章主要呈现齐美尔关于社交（Sociability）的理论片段，强调其作为社会化纯粹形式的属性。",
  "structure_pattern": "固定模板式",
  "section_functions": [
    "标题指明主题与日期",
    "核心语录展示",
    "视觉引导"
  ],
  "argument_moves": [
    "名家观点引述"
  ],
  "core_argument": "由于正文内容缺失，仅能判断其核心围绕齐美尔对社交的社会学定义展开。",
  "key_points": [
    "齐美尔社交理论",
    "每日阅读习惯培养"
  ],
  "opening_pattern": "直陈式",
  "ending_pattern": "闭环式",
  "evidence_types": [
    "名言语录"
  ],
  "evidence_specificity_score": 20,
  "data_density_score": 10,
  "case_density_score": 5,
  "quote_density_score": 80,
  "narrative_distance": "中立观察",
  "stance_strength": "中立",
  "sentence_rhythm": "短促",
  "abstraction_level": "高",
  "transferable_moves": [
    "使用'名家+日期'作为固定日更栏目提升品牌黏性"
  ],
  "anti_patterns": [
    "内容极度缺失导致无法形成独立论证",
    "过度依赖外部链接"
  ],
  "notable_phrases": [
    "齐美尔论社交",
    "FBK翻书日签"
  ],
  "title_score": 40,
  "opening_score": 20,
  "argument_score": 10,
  "evidence_score": 20,
  "structure_score": 30,
  "style_score": 40,
  "publishability_score": 20,
  "quality_score": 15,
  "reference_value_score": 10,
  "is_activity_notice": false,
  "is_low_value": true,
  "summary_200": "该内容为“FBK翻书”栏目的每日日签，发布于2024年2月26日。主题聚焦于德国社会学家齐美尔关于“社交”的论述。内容形式极简，主要作为社交媒体的日常触达物料。由于提供的文本仅包含标题和基本元数据，缺乏实际论证过程和具体正文，其主要价值在于品牌仪式感的建立，而非深度知识输出。作为分析样本，其信息密度极低，属于低价值的结构化数据源。",
  "summary_500": "本篇内容属于社交媒体平台（微信公众号）常见的“日签”类内容，标题为《齐美尔论社交丨FBK翻书日签 2024年2月26日》。从结构上看，这是一种标准化的碎片内容生产模式，旨在通过每日分享名家金句或学术观点片段，维持品牌与读者的互动。文章的主题定位在社会学领域的经典人物——齐美尔（Georg Simmel），探讨其关于社交（Sociability）的纯粹形式理论。在写作机制上，该文不具备完整的逻辑推演，而是采用直接引证的方式，将抽象的社会学概念转化为易于传播的视觉化文字。然而，由于本次提供的分析文本除了标题、日期和链接外，未包含实际的语录正文或评论分析，导致其在证据特征、论证深度及数据密度上表现极低。这种内容类型在商业运营中主要起到“心智占领”和“日常维护”的作用，而非提供深度的学术探讨或决策支持。对于追求高质量RAG写作和人格提炼的系统而言，此类信息的参考价值极小，标记为低价值。其唯一可迁移的动作是这种标准化的日更模板体系，适用于需要保持高频社交存在感的机构或个人。"
}
