{
  "id": "a27898011497",
  "year": "2025",
  "date": "2025-07-23",
  "title": "中国AI医疗如何跨越专利悬崖与死亡之谷？",
  "relative_path": "2025/2025-07-23_中国AI医疗如何跨越专利悬崖与死亡之谷？.txt",
  "full_text_path": "C:\\Users\\LXG\\BizCase\\raw_materials\\2025\\2025-07-23_中国AI医疗如何跨越专利悬崖与死亡之谷？.txt",
  "char_count": 6591,
  "industry": [
    "医疗健康",
    "生物技术",
    "人工智能"
  ],
  "topic": [
    "科技成果转化",
    "AI医疗",
    "专利",
    "创新创业",
    "风险投资",
    "医疗器械",
    "生物医药"
  ],
  "genre": "深度分析",
  "style": [
    "学术",
    "分析性",
    "前瞻性"
  ],
  "audience": [
    "医疗从业者",
    "科研人员",
    "创业者",
    "投资人",
    "政策制定者",
    "企业管理者"
  ],
  "intent": [
    "分析问题",
    "提出解决方案",
    "提供参考",
    "启迪思考"
  ],
  "tone": [
    "客观",
    "严谨",
    "专业",
    "建设性"
  ],
  "structure_pattern": "总-分-总",
  "core_argument": "中国AI医疗领域在科技成果转化方面面临专利悬崖、死亡之谷和被动等待三大陷阱，借鉴美国顶尖医疗机构的成功经验，通过建立跨学科团队、改革评价体系、设立概念验证基金、升级技术转移办公室等方式，可以有效跨越这些障碍，实现从实验室到临床的顺利转化。",
  "key_points": [
    "中国AI医疗科技成果转化率低，面临“专利悬崖”（专利申请多转化少）、“死亡之谷”（成果难以商业化）和“被动等待”（TTO模式落后）三大陷阱。",
    "“专利悬崖”源于科研评价体系重论文轻转化，激励机制不足。",
    "“死亡之谷”源于高昂的研发成本、早期资金断层和缺乏跨学科团队。",
    "“被动等待”源于技术转移办公室（TTO）定位陈旧，缺乏主动孵化能力。",
    "美国国家科学基金会I-Corps™项目通过严格审核、结构化培训和充足资助，构建“价值放大器”，利用“黄金三角”团队和客户访谈，成功降低早期创新风险。",
    "斯坦福大学Biodesign项目遵循“先需求，后技术”的原则，通过沉浸式需求挖掘，确保技术从源头就具备市场基因。",
    "麻省总医院/麻省理工（MGB/MIT）构建“临床-科研-产业”一体化生态，通过培养临床科学家、前瞻性布局、平台化支撑和资本化运作，深度融入创新转化。",
    "政策建议包括：改革职称评审，建立跨学科团队；设立医院级基金，鼓励“精益创新”；升级TTO为“孵化器经理”，关注价值导向指标；提供离岗创业期。",
    "真正的成果转化是一个持续的“创新培育”过程，需要生态化、主动化和全景思维。"
  ],
  "opening_pattern": "引入专家观点，提出核心问题",
  "ending_pattern": "总结性政策建议",
  "notable_phrases": [
    "专利悬崖",
    "死亡之谷",
    "最后一公里",
    "三大陷阱",
    "黄金三角",
    "先需求，后技术",
    "临床-科研-产业一体化生态",
    "价值放大器",
    "精益创新",
    "全景思维"
  ],
  "quality_score": 92.5,
  "reference_value_score": 95,
  "is_activity_notice": false,
  "is_low_value": false,
  "summary_200": "本文深度剖析了中国AI医疗领域在科技成果转化中面临的“专利悬崖”、“死亡之谷”和“被动等待”三大陷阱及其深层原因。文章借鉴了美国国家科学基金会I-Corps™、斯坦福大学Biodesign以及麻省总医院/麻省理工（MGB/MIT）等顶尖机构的成功经验，提出了破解之道。核心建议包括：改革评价体系、建立跨学科团队、设立概念验证基金、升级技术转移办公室功能，并强调成果转化是一个持续的“创新培育”过程，需要生态化、主动化和全景思维。文章为推动中国AI医疗创新转化提供了极具参考价值的思路与策略。",
  "summary_500": "本文针对中国AI医疗领域普遍存在的科技成果转化难题，即“专利悬崖”、“死亡之谷”和“被动等待”三大陷阱，进行了深入的分析与探讨。作者首先指出，尽管中国在AI医疗专利申请数量上表现不俗，但实际转化率极低，高校和科研机构的专利成果大多停留在实验室阶段，缺乏商业化路径和资源。三大陷阱的根源在于：科研评价体系重论文轻转化，抑制了临床医生的创新积极性；技术从实验室到产品的过程成本高昂，早期资金断层严重，跨学科人才匮乏；传统的技术转移办公室（TTO）定位被动，难以主动孵化和培育创新项目。为破解这些难题，文章详细介绍了美国三个顶尖医疗机构的解决方案。美国国家科学基金会（NSF）的I-Corps™项目通过严格筛选、结构化培训和提供种子基金，构建了一个“价值放大器”，其核心在于组建“黄金三角”团队（技术、执行、商业），并强制科学家进行大量客户访谈，从而有效降低早期风险，引导技术找到市场。斯坦福大学的Biodesign项目则强调“先需求，后技术”的理念，通过沉浸式需求挖掘，确保技术从源头就紧密贴合临床实际需求，大大提高了转化成功率。麻省总医院（MGB）与麻省理工学院（MIT）的合作模式，则展示了“临床-科研-产业”一体化生态系统的强大力量，他们通过培养临床科学家、设立概念验证基金、搭建平台化支持以及进行资本化运作，将创新转化深度融入日常医疗与科研工作。基于这些案例，文章提出了三方面的政策建议：一是通过改革职称评审、建立跨学科团队等方式破解“专利悬崖”；二是倡导组建“黄金三角”团队，设立阶梯式基金，鼓励“精益创新”文化，以跨越“死亡之谷”；三是升级TTO为主动的“孵化器经理”，关注价值导向指标，并为核心技术人员提供离岗创业期，以扭转“被动等待”局面。文章最后强调，真正的成果转化不是一次性交易，而是持续的“创新培育”过程，需要从孤立的TTO部门转向多方参与的创新生态，从“守株待兔”转向主动发现和培育，从仅关注技术转向“全景思维”，关注临床需求、商业模式、监管路径和支付闭环。整篇文章信息密度高，分析透彻，为中国AI医疗领域的创新发展提供了宝贵的实践指导和政策参考。"
}
